pdm_mypyc-0.1.0.dist-info/METADATA
pdm_mypyc-0.1.0.dist-info/WHEEL
pdm_mypyc-0.1.0.dist-info/entry_points.txt
pdm_mypyc-0.1.0.dist-info/licenses/LICENSE
pdm_mypyc.py
pdm_mypyc-0.1.0.dist-info/RECORD
