Metadata-Version: 2.1
Name: pdm-mypyc
Version: 0.1.0
Summary: A PDM build hook to compile source files with mypyc
Author-Email: Frost Ming <me@frostming.com>
License: MIT
Classifier: Programming Language :: Python :: 3
Classifier: Programming Language :: Python :: 3.7
Classifier: Programming Language :: Python :: 3.8
Classifier: Programming Language :: Python :: 3.9
Classifier: Programming Language :: Python :: 3.10
Classifier: Programming Language :: Python :: 3.11
Classifier: Programming Language :: Python :: 3 :: Only
Project-URL: Homepage, https://github.com/frostming/pdm-mypyc
Project-URL: Changelog, https://github.com/frostming/pdm-mypyc/releases
Requires-Python: >=3.7
Requires-Dist: mypy
Requires-Dist: setuptools
Requires-Dist: pdm-backend
